wow_print/__init__.py
wow_print/color_utils.py
wow_print-0.3.0.dist-info/LICENSE
wow_print-0.3.0.dist-info/METADATA
wow_print-0.3.0.dist-info/WHEEL
wow_print-0.3.0.dist-info/top_level.txt
wow_print-0.3.0.dist-info/RECORD
